README.md
mesa_behaviors/__init__.py
mesa_behaviors/agents/__init__.py
mesa_behaviors/agents/base_agent.py
mesa_behaviors/agents/distribution.py
mesa_behaviors/agents/population.py
mesa_behaviors/history/__init__.py
mesa_behaviors/history/base_history.py
mesa_behaviors/history/binary.py
mesa_behaviors/models/base_model.py
mesa_behaviors/strategies/__init__.py
mesa_behaviors/strategies/binary_strategy.py
mesa_behaviors/strategies/strategy.py
mesa_behaviors/utility/__init__.py
mesa_behaviors/utility/base_utility.py
mesa_behaviors/utility/binary.py
mesa_behaviors-0.1.0.dist-info/LICENSE
mesa_behaviors-0.1.0.dist-info/WHEEL
mesa_behaviors-0.1.0.dist-info/METADATA
mesa_behaviors-0.1.0.dist-info/RECORD
