Metadata-Version: 2.1
Name: mesa-behaviors
Version: 0.1.0
Summary: A framework for developing shareable Mesa Agents, Models and creating extensible Utility functions
Home-page: https://github.com/tokesim/mesa_behaviors
Keywords: mesa,ABM,tokesim,simulation,agent,modeling,mulit-agent
Author: Zane Starr
Author-email: zcstarr@gmail.com
Requires-Python: >=3.7,<3.8
Classifier: Intended Audience :: Developers
Classifier: License :: OSI Approved :: Apache Software License
Classifier: Natural Language :: English
Classifier: Operating System :: OS Independent
Classifier: Programming Language :: Python
Classifier: Programming Language :: Python :: 3
Classifier: Programming Language :: Python :: 3 :: Only
Classifier: Programming Language :: Python :: 3.7
Classifier: Programming Language :: Python :: 3.8
Classifier: Topic :: Scientific/Engineering
Classifier: Topic :: Scientific/Engineering :: Artificial Intelligence
Classifier: Topic :: Scientific/Engineering :: Artificial Life
Requires-Dist: bitarray (>=1.2.1,<2.0.0)
Requires-Dist: codecov (>=2.0.22,<3.0.0)
Requires-Dist: mesa (>=0.8.6,<0.9.0)
Requires-Dist: python-semantic-release (>=5.2.0,<6.0.0)
Requires-Dist: tox (>=3.14.6,<4.0.0)
Project-URL: Repository, https://github.com/tokesim/mesa_behaviors
